[
    {
        "name": "旁白",
        "text": "这一次，他站在熙熙攘攘的市集上，四周是粗布麻衣的行人",
        "imgpath": "./assets/image/chara/null.png",
        "bkpath": "./assets/image/level/6/background.png"
    },
    {
        "name": "旁白",
        "text": "远处传来糖葫芦小贩的吆喝声",
        "imgpath": "./assets/image/chara/null.png",
        "bkpath": "./assets/image/level/6/background.png"
    },
    {
        "name": "林夏",
        "text": "（低头看了看自己）得，这次是个江湖骗子",
        "imgpath": "./assets/image/chara/null.png",
        "bkpath": "./assets/image/level/6/background.png"
    },
    {
        "name": "旁白",
        "text": "忽然听到不远处传来清脆的女声",
        "imgpath": "./assets/image/chara/null.png",
        "bkpath": "./assets/image/level/6/background.png"
    },
    {
        "name": "少女",
        "text": "这位大娘，您这面相可是富贵相啊！",
        "imgpath": "./assets/image/chara/magic_girl.png",
        "bkpath": "./assets/image/level/6/background.png"
    },
    {
        "name": "少女",
        "text": "只是最近家中灶神不安，得破点小财消灾......",
        "imgpath": "./assets/image/chara/magic_girl_smile.png",
        "bkpath": "./assets/image/level/6/background.png"
    },
    {
        "name": "旁白",
        "text": "林夏猛地转头",
        "imgpath": "./assets/image/chara/null.png",
        "bkpath": "./assets/image/level/6/background.png"
    },
    {
        "name": "旁白",
        "text": "街角的小摊前，一个拿着符纸的少女正拉着一位老妇人的手",
        "imgpath": "./assets/image/chara/null.png",
        "bkpath": "./assets/image/level/6/background.png"
    },
    {
        "name": "林夏",
        "text": "（不自觉地靠近）",
        "imgpath": "./assets/image/chara/null.png",
        "bkpath": "./assets/image/level/6/background.png"
    },
    {
        "name": "林夏",
        "text": "（挤进人群，故意大声咳嗽）这位姑娘，您刚才说大娘“灶神不安",
        "imgpath": "./assets/image/chara/null.png",
        "bkpath": "./assets/image/level/6/background.png"
    },
    {
        "name": "林夏",
        "text": "（挤进人群，故意大声咳嗽）这位姑娘，您刚才说大娘“灶神不安”",
        "imgpath": "./assets/image/chara/null.png",
        "bkpath": "./assets/image/level/6/background.png"
    },
    {
        "name": "林夏",
        "text": "可今日是丙寅日，灶君当值，最是安稳不过啊……",
        "imgpath": "./assets/image/chara/null.png",
        "bkpath": "./assets/image/level/6/background.png"
    },
    {
        "name": "少女",
        "text": "不是……哥你谁啊",
        "imgpath": "./assets/image/chara/magic_girl_love.png",
        "bkpath": "./assets/image/level/6/background.png"
    },
    {
        "name": "少女",
        "text": "灶君当值就一定安稳了？纯傻*",
        "imgpath": "./assets/image/chara/magic_girl_smile.png",
        "bkpath": "./assets/image/level/6/background.png"
    },
    {
        "name": "林夏",
        "text": "来来……奶*的",
        "imgpath": "./assets/image/chara/null.png",
        "bkpath": "./assets/image/level/6/background.png"
    },
    {
        "name": "旁白",
        "text": "两人开始争辩……",
        "imgpath": "./assets/image/chara/null.png",
        "bkpath": "./assets/image/level/6/background.png"
    }
]